user/sim/basic_tb.v
module basic_tb();

    parameter DATA_WIDTH = 8;
    parameter ADDR_WIDTH = 8;
    parameter MAIN_FRE   = 100; //unit MHz
    reg                   sys_clk = 1;
    reg                   sys_rst = 1;
    reg [DATA_WIDTH-1:0]  data;

    always begin
        #(500/MAIN_FRE) sys_clk <= ~sys_clk;
    end

    always begin
        #45 sys_rst <= 0;
    end

    // rst as valid 
    // always @(posedge sys_clk or posedge sys_rst) begin
    //     if (sys_rst) begin
    //         data <= 0;
    //     end
    //     else begin
    //         data <= data + 1;
    //     end
    // end

    // valid after rst
    // reg ivalid;
    // always @(posedge sys_clk or posedge sys_rst) begin
    //     if (sys_rst) begin
    //         ivalid <= 0;
    //     end
    //     else begin
    //         ivalid <= 1;
    //     end
    // end

    always @(posedge sys_clk or posedge sys_rst) begin
        if (sys_rst) begin
            data <= 0;
        end
        else begin
            if (~sys_rst) begin
                data <= data + 1;
            end
        end
    end

    reg                   ovalid;
    reg [DATA_WIDTH-1:0]  odata;
    always @(posedge sys_clk or posedge sys_rst) begin
        if (sys_rst) begin
            ovalid <= 0;
            odata <= 0;
        end 
        else begin            
            if (~sys_rst) begin
                ovalid <= ~sys_rst;
                odata <= data;
            end
        end
    end

    // display & strobe
    always @(posedge sys_clk) begin
        if (~sys_rst) begin
            $display("$display :\tivalid:%d\tdata:%d", ~sys_rst, $signed(data));
            // $strobe("$strobe :\tivalid:%d\tdata:%d", ~sys_rst, $signed(data));
        end
    end

    initial begin
        $dumpfile("basic_tb.vcd");        
        $dumpvars(0, basic_tb);    
        #5000 $finish;
    end


endmodule  //TOP

basic_tb.vcd
$date
	Fri Jan  3 21:07:05 2025
$end
$version
	Icarus Verilog
$end
$timescale
	1s
$end
$scope module basic_tb $end
$var reg 8 ! data [7:0] $end
$var reg 8 " odata [7:0] $end
$var reg 1 # ovalid $end
$var reg 1 $ sys_clk $end
$var reg 1 % sys_rst $end
$upscope $end
$enddefinitions $end
#0
$dumpvars
1%
1$
x#
bx "
bx !
$end
#5
0$
#10
b0 !
b0 "
0#
1$
#15
0$
#20
1$
#25
0$
#30
1$
#35
0$
#40
1$
#45
0$
0%
#50
b1 !
1#
1$
#55
0$
#60
b1 "
b10 !
1$
#65
0$
#70
b11 !
b10 "
1$
#75
0$
#80
b11 "
b100 !
1$
#85
0$
#90
b101 !
b100 "
1$
#95
0$
#100
b101 "
b110 !
1$
#105
0$
#110
b111 !
b110 "
1$
#115
0$
#120
b111 "
b1000 !
1$
#125
0$
#130
b1001 !
b1000 "
1$
#135
0$
#140
b1001 "
b1010 !
1$
#145
0$
#150
b1011 !
b1010 "
1$
#155
0$
#160
b1011 "
b1100 !
1$
#165
0$
#170
b1101 !
b1100 "
1$
#175
0$
#180
b1101 "
b1110 !
1$
#185
0$
#190
b1111 !
b1110 "
1$
#195
0$
#200
b1111 "
b10000 !
1$
#205
0$
#210
b10001 !
b10000 "
1$
#215
0$
#220
b10001 "
b10010 !
1$
#225
0$
#230
b10011 !
b10010 "
1$
#235
0$
#240
b10011 "
b10100 !
1$
#245
0$
#250
b10101 !
b10100 "
1$
#255
0$
#260
b10101 "
b10110 !
1$
#265
0$
#270
b10111 !
b10110 "
1$
#275
0$
#280
b10111 "
b11000 !
1$
#285
0$
#290
b11001 !
b11000 "
1$
#295
0$
#300
b11001 "
b11010 !
1$
#305
0$
#310
b11011 !
b11010 "
1$
#315
0$
#320
b11011 "
b11100 !
1$
#325
0$
#330
b11101 !
b11100 "
1$
#335
0$
#340
b11101 "
b11110 !
1$
#345
0$
#350
b11111 !
b11110 "
1$
#355
0$
#360
b11111 "
b100000 !
1$
#365
0$
#370
b100001 !
b100000 "
1$
#375
0$
#380
b100001 "
b100010 !
1$
#385
0$
#390
b100011 !
b100010 "
1$
#395
0$
#400
b100011 "
b100100 !
1$
#405
0$
#410
b100101 !
b100100 "
1$
#415
0$
#420
b100101 "
b100110 !
1$
#425
0$
#430
b100111 !
b100110 "
1$
#435
0$
#440
b100111 "
b101000 !
1$
#445
0$
#450
b101001 !
b101000 "
1$
#455
0$
#460
b101001 "
b101010 !
1$
#465
0$
#470
b101011 !
b101010 "
1$
#475
0$
#480
b101011 "
b101100 !
1$
#485
0$
#490
b101101 !
b101100 "
1$
#495
0$
#500
b101101 "
b101110 !
1$
#505
0$
#510
b101111 !
b101110 "
1$
#515
0$
#520
b101111 "
b110000 !
1$
#525
0$
#530
b110001 !
b110000 "
1$
#535
0$
#540
b110001 "
b110010 !
1$
#545
0$
#550
b110011 !
b110010 "
1$
#555
0$
#560
b110011 "
b110100 !
1$
#565
0$
#570
b110101 !
b110100 "
1$
#575
0$
#580
b110101 "
b110110 !
1$
#585
0$
#590
b110111 !
b110110 "
1$
#595
0$
#600
b110111 "
b111000 !
1$
#605
0$
#610
b111001 !
b111000 "
1$
#615
0$
#620
b111001 "
b111010 !
1$
#625
0$
#630
b111011 !
b111010 "
1$
#635
0$
#640
b111011 "
b111100 !
1$
#645
0$
#650
b111101 !
b111100 "
1$
#655
0$
#660
b111101 "
b111110 !
1$
#665
0$
#670
b111111 !
b111110 "
1$
#675
0$
#680
b111111 "
b1000000 !
1$
#685
0$
#690
b1000001 !
b1000000 "
1$
#695
0$
#700
b1000001 "
b1000010 !
1$
#705
0$
#710
b1000011 !
b1000010 "
1$
#715
0$
#720
b1000011 "
b1000100 !
1$
#725
0$
#730
b1000101 !
b1000100 "
1$
#735
0$
#740
b1000101 "
b1000110 !
1$
#745
0$
#750
b1000111 !
b1000110 "
1$
#755
0$
#760
b1000111 "
b1001000 !
1$
#765
0$
#770
b1001001 !
b1001000 "
1$
#775
0$
#780
b1001001 "
b1001010 !
1$
#785
0$
#790
b1001011 !
b1001010 "
1$
#795
0$
#800
b1001011 "
b1001100 !
1$
#805
0$
#810
b1001101 !
b1001100 "
1$
#815
0$
#820
b1001101 "
b1001110 !
1$
#825
0$
#830
b1001111 !
b1001110 "
1$
#835
0$
#840
b1001111 "
b1010000 !
1$
#845
0$
#850
b1010001 !
b1010000 "
1$
#855
0$
#860
b1010001 "
b1010010 !
1$
#865
0$
#870
b1010011 !
b1010010 "
1$
#875
0$
#880
b1010011 "
b1010100 !
1$
#885
0$
#890
b1010101 !
b1010100 "
1$
#895
0$
#900
b1010101 "
b1010110 !
1$
#905
0$
#910
b1010111 !
b1010110 "
1$
#915
0$
#920
b1010111 "
b1011000 !
1$
#925
0$
#930
b1011001 !
b1011000 "
1$
#935
0$
#940
b1011001 "
b1011010 !
1$
#945
0$
#950
b1011011 !
b1011010 "
1$
#955
0$
#960
b1011011 "
b1011100 !
1$
#965
0$
#970
b1011101 !
b1011100 "
1$
#975
0$
#980
b1011101 "
b1011110 !
1$
#985
0$
#990
b1011111 !
b1011110 "
1$
#995
0$
#1000
b1011111 "
b1100000 !
1$
#1005
0$
#1010
b1100001 !
b1100000 "
1$
#1015
0$
#1020
b1100001 "
b1100010 !
1$
#1025
0$
#1030
b1100011 !
b1100010 "
1$
#1035
0$
#1040
b1100011 "
b1100100 !
1$
#1045
0$
#1050
b1100101 !
b1100100 "
1$
#1055
0$
#1060
b1100101 "
b1100110 !
1$
#1065
0$
#1070
b1100111 !
b1100110 "
1$
#1075
0$
#1080
b1100111 "
b1101000 !
1$
#1085
0$
#1090
b1101001 !
b1101000 "
1$
#1095
0$
#1100
b1101001 "
b1101010 !
1$
#1105
0$
#1110
b1101011 !
b1101010 "
1$
#1115
0$
#1120
b1101011 "
b1101100 !
1$
#1125
0$
#1130
b1101101 !
b1101100 "
1$
#1135
0$
#1140
b1101101 "
b1101110 !
1$
#1145
0$
#1150
b1101111 !
b1101110 "
1$
#1155
0$
#1160
b1101111 "
b1110000 !
1$
#1165
0$
#1170
b1110001 !
b1110000 "
1$
#1175
0$
#1180
b1110001 "
b1110010 !
1$
#1185
0$
#1190
b1110011 !
b1110010 "
1$
#1195
0$
#1200
b1110011 "
b1110100 !
1$
#1205
0$
#1210
b1110101 !
b1110100 "
1$
#1215
0$
#1220
b1110101 "
b1110110 !
1$
#1225
0$
#1230
b1110111 !
b1110110 "
1$
#1235
0$
#1240
b1110111 "
b1111000 !
1$
#1245
0$
#1250
b1111001 !
b1111000 "
1$
#1255
0$
#1260
b1111001 "
b1111010 !
1$
#1265
0$
#1270
b1111011 !
b1111010 "
1$
#1275
0$
#1280
b1111011 "
b1111100 !
1$
#1285
0$
#1290
b1111101 !
b1111100 "
1$
#1295
0$
#1300
b1111101 "
b1111110 !
1$
#1305
0$
#1310
b1111111 !
b1111110 "
1$
#1315
0$
#1320
b1111111 "
b10000000 !
1$
#1325
0$
#1330
b10000001 !
b10000000 "
1$
#1335
0$
#1340
b10000001 "
b10000010 !
1$
#1345
0$
#1350
b10000011 !
b10000010 "
1$
#1355
0$
#1360
b10000011 "
b10000100 !
1$
#1365
0$
#1370
b10000101 !
b10000100 "
1$
#1375
0$
#1380
b10000101 "
b10000110 !
1$
#1385
0$
#1390
b10000111 !
b10000110 "
1$
#1395
0$
#1400
b10000111 "
b10001000 !
1$
#1405
0$
#1410
b10001001 !
b10001000 "
1$
#1415
0$
#1420
b10001001 "
b10001010 !
1$
#1425
0$
#1430
b10001011 !
b10001010 "
1$
#1435
0$
#1440
b10001011 "
b10001100 !
1$
#1445
0$
#1450
b10001101 !
b10001100 "
1$
#1455
0$
#1460
b10001101 "
b10001110 !
1$
#1465
0$
#1470
b10001111 !
b10001110 "
1$
#1475
0$
#1480
b10001111 "
b10010000 !
1$
#1485
0$
#1490
b10010001 !
b10010000 "
1$
#1495
0$
#1500
b10010001 "
b10010010 !
1$
#1505
0$
#1510
b10010011 !
b10010010 "
1$
#1515
0$
#1520
b10010011 "
b10010100 !
1$
#1525
0$
#1530
b10010101 !
b10010100 "
1$
#1535
0$
#1540
b10010101 "
b10010110 !
1$
#1545
0$
#1550
b10010111 !
b10010110 "
1$
#1555
0$
#1560
b10010111 "
b10011000 !
1$
#1565
0$
#1570
b10011001 !
b10011000 "
1$
#1575
0$
#1580
b10011001 "
b10011010 !
1$
#1585
0$
#1590
b10011011 !
b10011010 "
1$
#1595
0$
#1600
b10011011 "
b10011100 !
1$
#1605
0$
#1610
b10011101 !
b10011100 "
1$
#1615
0$
#1620
b10011101 "
b10011110 !
1$
#1625
0$
#1630
b10011111 !
b10011110 "
1$
#1635
0$
#1640
b10011111 "
b10100000 !
1$
#1645
0$
#1650
b10100001 !
b10100000 "
1$
#1655
0$
#1660
b10100001 "
b10100010 !
1$
#1665
0$
#1670
b10100011 !
b10100010 "
1$
#1675
0$
#1680
b10100011 "
b10100100 !
1$
#1685
0$
#1690
b10100101 !
b10100100 "
1$
#1695
0$
#1700
b10100101 "
b10100110 !
1$
#1705
0$
#1710
b10100111 !
b10100110 "
1$
#1715
0$
#1720
b10100111 "
b10101000 !
1$
#1725
0$
#1730
b10101001 !
b10101000 "
1$
#1735
0$
#1740
b10101001 "
b10101010 !
1$
#1745
0$
#1750
b10101011 !
b10101010 "
1$
#1755
0$
#1760
b10101011 "
b10101100 !
1$
#1765
0$
#1770
b10101101 !
b10101100 "
1$
#1775
0$
#1780
b10101101 "
b10101110 !
1$
#1785
0$
#1790
b10101111 !
b10101110 "
1$
#1795
0$
#1800
b10101111 "
b10110000 !
1$
#1805
0$
#1810
b10110001 !
b10110000 "
1$
#1815
0$
#1820
b10110001 "
b10110010 !
1$
#1825
0$
#1830
b10110011 !
b10110010 "
1$
#1835
0$
#1840
b10110011 "
b10110100 !
1$
#1845
0$
#1850
b10110101 !
b10110100 "
1$
#1855
0$
#1860
b10110101 "
b10110110 !
1$
#1865
0$
#1870
b10110111 !
b10110110 "
1$
#1875
0$
#1880
b10110111 "
b10111000 !
1$
#1885
0$
#1890
b10111001 !
b10111000 "
1$
#1895
0$
#1900
b10111001 "
b10111010 !
1$
#1905
0$
#1910
b10111011 !
b10111010 "
1$
#1915
0$
#1920
b10111011 "
b10111100 !
1$
#1925
0$
#1930
b10111101 !
b10111100 "
1$
#1935
0$
#1940
b10111101 "
b10111110 !
1$
#1945
0$
#1950
b10111111 !
b10111110 "
1$
#1955
0$
#1960
b10111111 "
b11000000 !
1$
#1965
0$
#1970
b11000001 !
b11000000 "
1$
#1975
0$
#1980
b11000001 "
b11000010 !
1$
#1985
0$
#1990
b11000011 !
b11000010 "
1$
#1995
0$
#2000
b11000011 "
b11000100 !
1$
#2005
0$
#2010
b11000101 !
b11000100 "
1$
#2015
0$
#2020
b11000101 "
b11000110 !
1$
#2025
0$
#2030
b11000111 !
b11000110 "
1$
#2035
0$
#2040
b11000111 "
b11001000 !
1$
#2045
0$
#2050
b11001001 !
b11001000 "
1$
#2055
0$
#2060
b11001001 "
b11001010 !
1$
#2065
0$
#2070
b11001011 !
b11001010 "
1$
#2075
0$
#2080
b11001011 "
b11001100 !
1$
#2085
0$
#2090
b11001101 !
b11001100 "
1$
#2095
0$
#2100
b11001101 "
b11001110 !
1$
#2105
0$
#2110
b11001111 !
b11001110 "
1$
#2115
0$
#2120
b11001111 "
b11010000 !
1$
#2125
0$
#2130
b11010001 !
b11010000 "
1$
#2135
0$
#2140
b11010001 "
b11010010 !
1$
#2145
0$
#2150
b11010011 !
b11010010 "
1$
#2155
0$
#2160
b11010011 "
b11010100 !
1$
#2165
0$
#2170
b11010101 !
b11010100 "
1$
#2175
0$
#2180
b11010101 "
b11010110 !
1$
#2185
0$
#2190
b11010111 !
b11010110 "
1$
#2195
0$
#2200
b11010111 "
b11011000 !
1$
#2205
0$
#2210
b11011001 !
b11011000 "
1$
#2215
0$
#2220
b11011001 "
b11011010 !
1$
#2225
0$
#2230
b11011011 !
b11011010 "
1$
#2235
0$
#2240
b11011011 "
b11011100 !
1$
#2245
0$
#2250
b11011101 !
b11011100 "
1$
#2255
0$
#2260
b11011101 "
b11011110 !
1$
#2265
0$
#2270
b11011111 !
b11011110 "
1$
#2275
0$
#2280
b11011111 "
b11100000 !
1$
#2285
0$
#2290
b11100001 !
b11100000 "
1$
#2295
0$
#2300
b11100001 "
b11100010 !
1$
#2305
0$
#2310
b11100011 !
b11100010 "
1$
#2315
0$
#2320
b11100011 "
b11100100 !
1$
#2325
0$
#2330
b11100101 !
b11100100 "
1$
#2335
0$
#2340
b11100101 "
b11100110 !
1$
#2345
0$
#2350
b11100111 !
b11100110 "
1$
#2355
0$
#2360
b11100111 "
b11101000 !
1$
#2365
0$
#2370
b11101001 !
b11101000 "
1$
#2375
0$
#2380
b11101001 "
b11101010 !
1$
#2385
0$
#2390
b11101011 !
b11101010 "
1$
#2395
0$
#2400
b11101011 "
b11101100 !
1$
#2405
0$
#2410
b11101101 !
b11101100 "
1$
#2415
0$
#2420
b11101101 "
b11101110 !
1$
#2425
0$
#2430
b11101111 !
b11101110 "
1$
#2435
0$
#2440
b11101111 "
b11110000 !
1$
#2445
0$
#2450
b11110001 !
b11110000 "
1$
#2455
0$
#2460
b11110001 "
b11110010 !
1$
#2465
0$
#2470
b11110011 !
b11110010 "
1$
#2475
0$
#2480
b11110011 "
b11110100 !
1$
#2485
0$
#2490
b11110101 !
b11110100 "
1$
#2495
0$
#2500
b11110101 "
b11110110 !
1$
#2505
0$
#2510
b11110111 !
b11110110 "
1$
#2515
0$
#2520
b11110111 "
b11111000 !
1$
#2525
0$
#2530
b11111001 !
b11111000 "
1$
#2535
0$
#2540
b11111001 "
b11111010 !
1$
#2545
0$
#2550
b11111011 !
b11111010 "
1$
#2555
0$
#2560
b11111011 "
b11111100 !
1$
#2565
0$
#2570
b11111101 !
b11111100 "
1$
#2575
0$
#2580
b11111101 "
b11111110 !
1$
#2585
0$
#2590
b11111111 !
b11111110 "
1$
#2595
0$
#2600
b11111111 "
b0 !
1$
#2605
0$
#2610
b1 !
b0 "
1$
#2615
0$
#2620
b1 "
b10 !
1$
#2625
0$
#2630
b11 !
b10 "
1$
#2635
0$
#2640
b11 "
b100 !
1$
#2645
0$
#2650
b101 !
b100 "
1$
#2655
0$
#2660
b101 "
b110 !
1$
#2665
0$
#2670
b111 !
b110 "
1$
#2675
0$
#2680
b111 "
b1000 !
1$
#2685
0$
#2690
b1001 !
b1000 "
1$
#2695
0$
#2700
b1001 "
b1010 !
1$
#2705
0$
#2710
b1011 !
b1010 "
1$
#2715
0$
#2720
b1011 "
b1100 !
1$
#2725
0$
#2730
b1101 !
b1100 "
1$
#2735
0$
#2740
b1101 "
b1110 !
1$
#2745
0$
#2750
b1111 !
b1110 "
1$
#2755
0$
#2760
b1111 "
b10000 !
1$
#2765
0$
#2770
b10001 !
b10000 "
1$
#2775
0$
#2780
b10001 "
b10010 !
1$
#2785
0$
#2790
b10011 !
b10010 "
1$
#2795
0$
#2800
b10011 "
b10100 !
1$
#2805
0$
#2810
b10101 !
b10100 "
1$
#2815
0$
#2820
b10101 "
b10110 !
1$
#2825
0$
#2830
b10111 !
b10110 "
1$
#2835
0$
#2840
b10111 "
b11000 !
1$
#2845
0$
#2850
b11001 !
b11000 "
1$
#2855
0$
#2860
b11001 "
b11010 !
1$
#2865
0$
#2870
b11011 !
b11010 "
1$
#2875
0$
#2880
b11011 "
b11100 !
1$
#2885
0$
#2890
b11101 !
b11100 "
1$
#2895
0$
#2900
b11101 "
b11110 !
1$
#2905
0$
#2910
b11111 !
b11110 "
1$
#2915
0$
#2920
b11111 "
b100000 !
1$
#2925
0$
#2930
b100001 !
b100000 "
1$
#2935
0$
#2940
b100001 "
b100010 !
1$
#2945
0$
#2950
b100011 !
b100010 "
1$
#2955
0$
#2960
b100011 "
b100100 !
1$
#2965
0$
#2970
b100101 !
b100100 "
1$
#2975
0$
#2980
b100101 "
b100110 !
1$
#2985
0$
#2990
b100111 !
b100110 "
1$
#2995
0$
#3000
b100111 "
b101000 !
1$
#3005
0$
#3010
b101001 !
b101000 "
1$
#3015
0$
#3020
b101001 "
b101010 !
1$
#3025
0$
#3030
b101011 !
b101010 "
1$
#3035
0$
#3040
b101011 "
b101100 !
1$
#3045
0$
#3050
b101101 !
b101100 "
1$
#3055
0$
#3060
b101101 "
b101110 !
1$
#3065
0$
#3070
b101111 !
b101110 "
1$
#3075
0$
#3080
b101111 "
b110000 !
1$
#3085
0$
#3090
b110001 !
b110000 "
1$
#3095
0$
#3100
b110001 "
b110010 !
1$
#3105
0$
#3110
b110011 !
b110010 "
1$
#3115
0$
#3120
b110011 "
b110100 !
1$
#3125
0$
#3130
b110101 !
b110100 "
1$
#3135
0$
#3140
b110101 "
b110110 !
1$
#3145
0$
#3150
b110111 !
b110110 "
1$
#3155
0$
#3160
b110111 "
b111000 !
1$
#3165
0$
#3170
b111001 !
b111000 "
1$
#3175
0$
#3180
b111001 "
b111010 !
1$
#3185
0$
#3190
b111011 !
b111010 "
1$
#3195
0$
#3200
b111011 "
b111100 !
1$
#3205
0$
#3210
b111101 !
b111100 "
1$
#3215
0$
#3220
b111101 "
b111110 !
1$
#3225
0$
#3230
b111111 !
b111110 "
1$
#3235
0$
#3240
b111111 "
b1000000 !
1$
#3245
0$
#3250
b1000001 !
b1000000 "
1$
#3255
0$
#3260
b1000001 "
b1000010 !
1$
#3265
0$
#3270
b1000011 !
b1000010 "
1$
#3275
0$
#3280
b1000011 "
b1000100 !
1$
#3285
0$
#3290
b1000101 !
b1000100 "
1$
#3295
0$
#3300
b1000101 "
b1000110 !
1$
#3305
0$
#3310
b1000111 !
b1000110 "
1$
#3315
0$
#3320
b1000111 "
b1001000 !
1$
#3325
0$
#3330
b1001001 !
b1001000 "
1$
#3335
0$
#3340
b1001001 "
b1001010 !
1$
#3345
0$
#3350
b1001011 !
b1001010 "
1$
#3355
0$
#3360
b1001011 "
b1001100 !
1$
#3365
0$
#3370
b1001101 !
b1001100 "
1$
#3375
0$
#3380
b1001101 "
b1001110 !
1$
#3385
0$
#3390
b1001111 !
b1001110 "
1$
#3395
0$
#3400
b1001111 "
b1010000 !
1$
#3405
0$
#3410
b1010001 !
b1010000 "
1$
#3415
0$
#3420
b1010001 "
b1010010 !
1$
#3425
0$
#3430
b1010011 !
b1010010 "
1$
#3435
0$
#3440
b1010011 "
b1010100 !
1$
#3445
0$
#3450
b1010101 !
b1010100 "
1$
#3455
0$
#3460
b1010101 "
b1010110 !
1$
#3465
0$
#3470
b1010111 !
b1010110 "
1$
#3475
0$
#3480
b1010111 "
b1011000 !
1$
#3485
0$
#3490
b1011001 !
b1011000 "
1$
#3495
0$
#3500
b1011001 "
b1011010 !
1$
#3505
0$
#3510
b1011011 !
b1011010 "
1$
#3515
0$
#3520
b1011011 "
b1011100 !
1$
#3525
0$
#3530
b1011101 !
b1011100 "
1$
#3535
0$
#3540
b1011101 "
b1011110 !
1$
#3545
0$
#3550
b1011111 !
b1011110 "
1$
#3555
0$
#3560
b1011111 "
b1100000 !
1$
#3565
0$
#3570
b1100001 !
b1100000 "
1$
#3575
0$
#3580
b1100001 "
b1100010 !
1$
#3585
0$
#3590
b1100011 !
b1100010 "
1$
#3595
0$
#3600
b1100011 "
b1100100 !
1$
#3605
0$
#3610
b1100101 !
b1100100 "
1$
#3615
0$
#3620
b1100101 "
b1100110 !
1$
#3625
0$
#3630
b1100111 !
b1100110 "
1$
#3635
0$
#3640
b1100111 "
b1101000 !
1$
#3645
0$
#3650
b1101001 !
b1101000 "
1$
#3655
0$
#3660
b1101001 "
b1101010 !
1$
#3665
0$
#3670
b1101011 !
b1101010 "
1$
#3675
0$
#3680
b1101011 "
b1101100 !
1$
#3685
0$
#3690
b1101101 !
b1101100 "
1$
#3695
0$
#3700
b1101101 "
b1101110 !
1$
#3705
0$
#3710
b1101111 !
b1101110 "
1$
#3715
0$
#3720
b1101111 "
b1110000 !
1$
#3725
0$
#3730
b1110001 !
b1110000 "
1$
#3735
0$
#3740
b1110001 "
b1110010 !
1$
#3745
0$
#3750
b1110011 !
b1110010 "
1$
#3755
0$
#3760
b1110011 "
b1110100 !
1$
#3765
0$
#3770
b1110101 !
b1110100 "
1$
#3775
0$
#3780
b1110101 "
b1110110 !
1$
#3785
0$
#3790
b1110111 !
b1110110 "
1$
#3795
0$
#3800
b1110111 "
b1111000 !
1$
#3805
0$
#3810
b1111001 !
b1111000 "
1$
#3815
0$
#3820
b1111001 "
b1111010 !
1$
#3825
0$
#3830
b1111011 !
b1111010 "
1$
#3835
0$
#3840
b1111011 "
b1111100 !
1$
#3845
0$
#3850
b1111101 !
b1111100 "
1$
#3855
0$
#3860
b1111101 "
b1111110 !
1$
#3865
0$
#3870
b1111111 !
b1111110 "
1$
#3875
0$
#3880
b1111111 "
b10000000 !
1$
#3885
0$
#3890
b10000001 !
b10000000 "
1$
#3895
0$
#3900
b10000001 "
b10000010 !
1$
#3905
0$
#3910
b10000011 !
b10000010 "
1$
#3915
0$
#3920
b10000011 "
b10000100 !
1$
#3925
0$
#3930
b10000101 !
b10000100 "
1$
#3935
0$
#3940
b10000101 "
b10000110 !
1$
#3945
0$
#3950
b10000111 !
b10000110 "
1$
#3955
0$
#3960
b10000111 "
b10001000 !
1$
#3965
0$
#3970
b10001001 !
b10001000 "
1$
#3975
0$
#3980
b10001001 "
b10001010 !
1$
#3985
0$
#3990
b10001011 !
b10001010 "
1$
#3995
0$
#4000
b10001011 "
b10001100 !
1$
#4005
0$
#4010
b10001101 !
b10001100 "
1$
#4015
0$
#4020
b10001101 "
b10001110 !
1$
#4025
0$
#4030
b10001111 !
b10001110 "
1$
#4035
0$
#4040
b10001111 "
b10010000 !
1$
#4045
0$
#4050
b10010001 !
b10010000 "
1$
#4055
0$
#4060
b10010001 "
b10010010 !
1$
#4065
0$
#4070
b10010011 !
b10010010 "
1$
#4075
0$
#4080
b10010011 "
b10010100 !
1$
#4085
0$
#4090
b10010101 !
b10010100 "
1$
#4095
0$
#4100
b10010101 "
b10010110 !
1$
#4105
0$
#4110
b10010111 !
b10010110 "
1$
#4115
0$
#4120
b10010111 "
b10011000 !
1$
#4125
0$
#4130
b10011001 !
b10011000 "
1$
#4135
0$
#4140
b10011001 "
b10011010 !
1$
#4145
0$
#4150
b10011011 !
b10011010 "
1$
#4155
0$
#4160
b10011011 "
b10011100 !
1$
#4165
0$
#4170
b10011101 !
b10011100 "
1$
#4175
0$
#4180
b10011101 "
b10011110 !
1$
#4185
0$
#4190
b10011111 !
b10011110 "
1$
#4195
0$
#4200
b10011111 "
b10100000 !
1$
#4205
0$
#4210
b10100001 !
b10100000 "
1$
#4215
0$
#4220
b10100001 "
b10100010 !
1$
#4225
0$
#4230
b10100011 !
b10100010 "
1$
#4235
0$
#4240
b10100011 "
b10100100 !
1$
#4245
0$
#4250
b10100101 !
b10100100 "
1$
#4255
0$
#4260
b10100101 "
b10100110 !
1$
#4265
0$
#4270
b10100111 !
b10100110 "
1$
#4275
0$
#4280
b10100111 "
b10101000 !
1$
#4285
0$
#4290
b10101001 !
b10101000 "
1$
#4295
0$
#4300
b10101001 "
b10101010 !
1$
#4305
0$
#4310
b10101011 !
b10101010 "
1$
#4315
0$
#4320
b10101011 "
b10101100 !
1$
#4325
0$
#4330
b10101101 !
b10101100 "
1$
#4335
0$
#4340
b10101101 "
b10101110 !
1$
#4345
0$
#4350
b10101111 !
b10101110 "
1$
#4355
0$
#4360
b10101111 "
b10110000 !
1$
#4365
0$
#4370
b10110001 !
b10110000 "
1$
#4375
0$
#4380
b10110001 "
b10110010 !
1$
#4385
0$
#4390
b10110011 !
b10110010 "
1$
#4395
0$
#4400
b10110011 "
b10110100 !
1$
#4405
0$
#4410
b10110101 !
b10110100 "
1$
#4415
0$
#4420
b10110101 "
b10110110 !
1$
#4425
0$
#4430
b10110111 !
b10110110 "
1$
#4435
0$
#4440
b10110111 "
b10111000 !
1$
#4445
0$
#4450
b10111001 !
b10111000 "
1$
#4455
0$
#4460
b10111001 "
b10111010 !
1$
#4465
0$
#4470
b10111011 !
b10111010 "
1$
#4475
0$
#4480
b10111011 "
b10111100 !
1$
#4485
0$
#4490
b10111101 !
b10111100 "
1$
#4495
0$
#4500
b10111101 "
b10111110 !
1$
#4505
0$
#4510
b10111111 !
b10111110 "
1$
#4515
0$
#4520
b10111111 "
b11000000 !
1$
#4525
0$
#4530
b11000001 !
b11000000 "
1$
#4535
0$
#4540
b11000001 "
b11000010 !
1$
#4545
0$
#4550
b11000011 !
b11000010 "
1$
#4555
0$
#4560
b11000011 "
b11000100 !
1$
#4565
0$
#4570
b11000101 !
b11000100 "
1$
#4575
0$
#4580
b11000101 "
b11000110 !
1$
#4585
0$
#4590
b11000111 !
b11000110 "
1$
#4595
0$
#4600
b11000111 "
b11001000 !
1$
#4605
0$
#4610
b11001001 !
b11001000 "
1$
#4615
0$
#4620
b11001001 "
b11001010 !
1$
#4625
0$
#4630
b11001011 !
b11001010 "
1$
#4635
0$
#4640
b11001011 "
b11001100 !
1$
#4645
0$
#4650
b11001101 !
b11001100 "
1$
#4655
0$
#4660
b11001101 "
b11001110 !
1$
#4665
0$
#4670
b11001111 !
b11001110 "
1$
#4675
0$
#4680
b11001111 "
b11010000 !
1$
#4685
0$
#4690
b11010001 !
b11010000 "
1$
#4695
0$
#4700
b11010001 "
b11010010 !
1$
#4705
0$
#4710
b11010011 !
b11010010 "
1$
#4715
0$
#4720
b11010011 "
b11010100 !
1$
#4725
0$
#4730
b11010101 !
b11010100 "
1$
#4735
0$
#4740
b11010101 "
b11010110 !
1$
#4745
0$
#4750
b11010111 !
b11010110 "
1$
#4755
0$
#4760
b11010111 "
b11011000 !
1$
#4765
0$
#4770
b11011001 !
b11011000 "
1$
#4775
0$
#4780
b11011001 "
b11011010 !
1$
#4785
0$
#4790
b11011011 !
b11011010 "
1$
#4795
0$
#4800
b11011011 "
b11011100 !
1$
#4805
0$
#4810
b11011101 !
b11011100 "
1$
#4815
0$
#4820
b11011101 "
b11011110 !
1$
#4825
0$
#4830
b11011111 !
b11011110 "
1$
#4835
0$
#4840
b11011111 "
b11100000 !
1$
#4845
0$
#4850
b11100001 !
b11100000 "
1$
#4855
0$
#4860
b11100001 "
b11100010 !
1$
#4865
0$
#4870
b11100011 !
b11100010 "
1$
#4875
0$
#4880
b11100011 "
b11100100 !
1$
#4885
0$
#4890
b11100101 !
b11100100 "
1$
#4895
0$
#4900
b11100101 "
b11100110 !
1$
#4905
0$
#4910
b11100111 !
b11100110 "
1$
#4915
0$
#4920
b11100111 "
b11101000 !
1$
#4925
0$
#4930
b11101001 !
b11101000 "
1$
#4935
0$
#4940
b11101001 "
b11101010 !
1$
#4945
0$
#4950
b11101011 !
b11101010 "
1$
#4955
0$
#4960
b11101011 "
b11101100 !
1$
#4965
0$
#4970
b11101101 !
b11101100 "
1$
#4975
0$
#4980
b11101101 "
b11101110 !
1$
#4985
0$
#4990
b11101111 !
b11101110 "
1$
#4995
0$
#5000
b11101111 "
b11110000 !
1$
